[1,["00Vgq+1hNA2ZUPKGIPuDJ5@6c48a","03pnxGqAtNXIkYL3zYUKdC@6c48a","1aAVVRvhJJ65UOblVYItJK@6c48a","30d2JXCudAzZWf+uCdqVtc@6c48a","488WRzLXpCjYfpUSC7ez/D@6c48a","58nmMrSy9NYrGXtV6y5jEn@6c48a","5chPLhMFBARrDalgFqebAy@6c48a","71jCFLrdVLpK/a1gUUykEA@6c48a","792qXhGjdHx6KG2LIuP5nu@6c48a","7egrV8921J0ryvkQqH6fmB@6c48a","81KmPIhPNGlqYS94FYRLYB@6c48a","8cNTxmk/dO4I8Kcr1KheyA@6c48a","92boBgxDBLiLUhtSeOiZEu@6c48a","adrQwGshhOLoxRysE0m2QM@6c48a","b5AEIDUDBIx4NUVtE7umk8@6c48a","bd9+f855dMBofh42i1PMr/@6c48a","be4vWCm6dO3LaR5FH1YbR/@6c48a","c0FvB57AVLqbF8/d7GHlw4@6c48a","c7m8dPvB5IV4YzFnNs6Tz1@6c48a","d2RpBiaQ5JwZG15RQjNM11@6c48a","d5Ev8TEsZBirF1BnuTrX0W@6c48a","d9+hdAY6hNuKTzcfRaIIed@6c48a","ddoc02TB5DC54KqRF5eEKS@6c48a","e4h48b9ftDWqHx2qaZ7CcU@6c48a","e8deP1EBhHI7NhjtegwBj8@6c48a","f6R0y6GeZP6b3bHoPflo9A@6c48a"],["_textureSource"],["cc.SpriteFrame"],0,[[[{"name":"lajiao-lajiaozhanshidonghua_07","rect":{"x":30,"y":0,"width":60,"height":84},"offset":{"x":-2.5,"y":0.5},"originalSize":{"width":125,"height":85},"rotated":false,"capInsets":[0,0,0,0],"vertices":{"rawPosition":[-30,-42,0,30,-42,0,-30,42,0,30,42,0],"indexes":[0,1,2,2,1,3],"uv":[30,85,90,85,30,1,90,1],"nuv":[0.24,0.011764705882352941,0.72,0.011764705882352941,0.24,1,0.72,1],"minPos":{"x":-30,"y":-42,"z":0},"maxPos":{"x":30,"y":42,"z":0}},"packable":false,"pixelsToUnit":100,"pivot":{"x":0.5,"y":0.5},"meshType":0}],[0],0,[0],[0],[0]],[[{"name":"lajiao-lajiaozhanshidonghua_10","rect":{"x":20,"y":0,"width":82,"height":84},"offset":{"x":-1.5,"y":0.5},"originalSize":{"width":125,"height":85},"rotated":false,"capInsets":[0,0,0,0],"vertices":{"rawPosition":[-41,-42,0,41,-42,0,-41,42,0,41,42,0],"indexes":[0,1,2,2,1,3],"uv":[20,85,102,85,20,1,102,1],"nuv":[0.16,0.011764705882352941,0.816,0.011764705882352941,0.16,1,0.816,1],"minPos":{"x":-41,"y":-42,"z":0},"maxPos":{"x":41,"y":42,"z":0}},"packable":false,"pixelsToUnit":100,"pivot":{"x":0.5,"y":0.5},"meshType":0}],[0],0,[0],[0],[1]],[[{"name":"lajiao-lajiaozhanshidonghua_11","rect":{"x":17,"y":0,"width":89,"height":84},"offset":{"x":-1,"y":0.5},"originalSize":{"width":125,"height":85},"rotated":false,"capInsets":[0,0,0,0],"vertices":{"rawPosition":[-44.5,-42,0,44.5,-42,0,-44.5,42,0,44.5,42,0],"indexes":[0,1,2,2,1,3],"uv":[17,85,106,85,17,1,106,1],"nuv":[0.136,0.011764705882352941,0.848,0.011764705882352941,0.136,1,0.848,1],"minPos":{"x":-44.5,"y":-42,"z":0},"maxPos":{"x":44.5,"y":42,"z":0}},"packable":false,"pixelsToUnit":100,"pivot":{"x":0.5,"y":0.5},"meshType":0}],[0],0,[0],[0],[2]],[[{"name":"lajiao-lajiaozhanshidonghua_18","rect":{"x":1,"y":0,"width":124,"height":84},"offset":{"x":0.5,"y":0.5},"originalSize":{"width":125,"height":85},"rotated":false,"capInsets":[0,0,0,0],"vertices":{"rawPosition":[-62,-42,0,62,-42,0,-62,42,0,62,42,0],"indexes":[0,1,2,2,1,3],"uv":[1,85,125,85,1,1,125,1],"nuv":[0.008,0.011764705882352941,1,0.011764705882352941,0.008,1,1,1],"minPos":{"x":-62,"y":-42,"z":0},"maxPos":{"x":62,"y":42,"z":0}},"packable":false,"pixelsToUnit":100,"pivot":{"x":0.5,"y":0.5},"meshType":0}],[0],0,[0],[0],[3]],[[{"name":"lajiao-lajiaozhanshidonghua_16","rect":{"x":1,"y":0,"width":124,"height":84},"offset":{"x":0.5,"y":0.5},"originalSize":{"width":125,"height":85},"rotated":false,"capInsets":[0,0,0,0],"vertices":{"rawPosition":[-62,-42,0,62,-42,0,-62,42,0,62,42,0],"indexes":[0,1,2,2,1,3],"uv":[1,85,125,85,1,1,125,1],"nuv":[0.008,0.011764705882352941,1,0.011764705882352941,0.008,1,1,1],"minPos":{"x":-62,"y":-42,"z":0},"maxPos":{"x":62,"y":42,"z":0}},"packable":false,"pixelsToUnit":100,"pivot":{"x":0.5,"y":0.5},"meshType":0}],[0],0,[0],[0],[4]],[[{"name":"lajiao-lajiaozhanshidonghua_08","rect":{"x":27,"y":0,"width":67,"height":84},"offset":{"x":-2,"y":0.5},"originalSize":{"width":125,"height":85},"rotated":false,"capInsets":[0,0,0,0],"vertices":{"rawPosition":[-33.5,-42,0,33.5,-42,0,-33.5,42,0,33.5,42,0],"indexes":[0,1,2,2,1,3],"uv":[27,85,94,85,27,1,94,1],"nuv":[0.216,0.011764705882352941,0.752,0.011764705882352941,0.216,1,0.752,1],"minPos":{"x":-33.5,"y":-42,"z":0},"maxPos":{"x":33.5,"y":42,"z":0}},"packable":false,"pixelsToUnit":100,"pivot":{"x":0.5,"y":0.5},"meshType":0}],[0],0,[0],[0],[5]],[[{"name":"lajiao-lajiaozhanshidonghua_12","rect":{"x":14,"y":0,"width":95,"height":84},"offset":{"x":-1,"y":0.5},"originalSize":{"width":125,"height":85},"rotated":false,"capInsets":[0,0,0,0],"vertices":{"rawPosition":[-47.5,-42,0,47.5,-42,0,-47.5,42,0,47.5,42,0],"indexes":[0,1,2,2,1,3],"uv":[14,85,109,85,14,1,109,1],"nuv":[0.112,0.011764705882352941,0.872,0.011764705882352941,0.112,1,0.872,1],"minPos":{"x":-47.5,"y":-42,"z":0},"maxPos":{"x":47.5,"y":42,"z":0}},"packable":false,"pixelsToUnit":100,"pivot":{"x":0.5,"y":0.5},"meshType":0}],[0],0,[0],[0],[6]],[[{"name":"lajiao-lajiaozhanshidonghua_23","rect":{"x":30,"y":1,"width":61,"height":83},"offset":{"x":-2,"y":0},"originalSize":{"width":125,"height":85},"rotated":false,"capInsets":[0,0,0,0],"vertices":{"rawPosition":[-30.5,-41.5,0,30.5,-41.5,0,-30.5,41.5,0,30.5,41.5,0],"indexes":[0,1,2,2,1,3],"uv":[30,84,91,84,30,1,91,1],"nuv":[0.24,0.011764705882352941,0.728,0.011764705882352941,0.24,0.9882352941176471,0.728,0.9882352941176471],"minPos":{"x":-30.5,"y":-41.5,"z":0},"maxPos":{"x":30.5,"y":41.5,"z":0}},"packable":false,"pixelsToUnit":100,"pivot":{"x":0.5,"y":0.5},"meshType":0}],[0],0,[0],[0],[7]],[[{"name":"lajiao-lajiaozhanshidonghua_22","rect":{"x":38,"y":1,"width":44,"height":83},"offset":{"x":-2.5,"y":0},"originalSize":{"width":125,"height":85},"rotated":false,"capInsets":[0,0,0,0],"vertices":{"rawPosition":[-22,-41.5,0,22,-41.5,0,-22,41.5,0,22,41.5,0],"indexes":[0,1,2,2,1,3],"uv":[38,84,82,84,38,1,82,1],"nuv":[0.304,0.011764705882352941,0.656,0.011764705882352941,0.304,0.9882352941176471,0.656,0.9882352941176471],"minPos":{"x":-22,"y":-41.5,"z":0},"maxPos":{"x":22,"y":41.5,"z":0}},"packable":false,"pixelsToUnit":100,"pivot":{"x":0.5,"y":0.5},"meshType":0}],[0],0,[0],[0],[8]],[[{"name":"lajiao-lajiaozhanshidonghua_19","rect":{"x":10,"y":0,"width":104,"height":84},"offset":{"x":-0.5,"y":0.5},"originalSize":{"width":125,"height":85},"rotated":false,"capInsets":[0,0,0,0],"vertices":{"rawPosition":[-52,-42,0,52,-42,0,-52,42,0,52,42,0],"indexes":[0,1,2,2,1,3],"uv":[10,85,114,85,10,1,114,1],"nuv":[0.08,0.011764705882352941,0.912,0.011764705882352941,0.08,1,0.912,1],"minPos":{"x":-52,"y":-42,"z":0},"maxPos":{"x":52,"y":42,"z":0}},"packable":false,"pixelsToUnit":100,"pivot":{"x":0.5,"y":0.5},"meshType":0}],[0],0,[0],[0],[9]],[[{"name":"lajiao-lajiaozhanshidonghua_24","rect":{"x":22,"y":0,"width":78,"height":84},"offset":{"x":-1.5,"y":0.5},"originalSize":{"width":125,"height":85},"rotated":false,"capInsets":[0,0,0,0],"vertices":{"rawPosition":[-39,-42,0,39,-42,0,-39,42,0,39,42,0],"indexes":[0,1,2,2,1,3],"uv":[22,85,100,85,22,1,100,1],"nuv":[0.176,0.011764705882352941,0.8,0.011764705882352941,0.176,1,0.8,1],"minPos":{"x":-39,"y":-42,"z":0},"maxPos":{"x":39,"y":42,"z":0}},"packable":false,"pixelsToUnit":100,"pivot":{"x":0.5,"y":0.5},"meshType":0}],[0],0,[0],[0],[10]],[[{"name":"lajiao-lajiaozhanshidonghua_15","rect":{"x":4,"y":0,"width":117,"height":84},"offset":{"x":0,"y":0.5},"originalSize":{"width":125,"height":85},"rotated":false,"capInsets":[0,0,0,0],"vertices":{"rawPosition":[-58.5,-42,0,58.5,-42,0,-58.5,42,0,58.5,42,0],"indexes":[0,1,2,2,1,3],"uv":[4,85,121,85,4,1,121,1],"nuv":[0.032,0.011764705882352941,0.968,0.011764705882352941,0.032,1,0.968,1],"minPos":{"x":-58.5,"y":-42,"z":0},"maxPos":{"x":58.5,"y":42,"z":0}},"packable":false,"pixelsToUnit":100,"pivot":{"x":0.5,"y":0.5},"meshType":0}],[0],0,[0],[0],[11]],[[{"name":"lajiao-lajiaozhanshidonghua_05","rect":{"x":37,"y":0,"width":46,"height":84},"offset":{"x":-2.5,"y":0.5},"originalSize":{"width":125,"height":85},"rotated":false,"capInsets":[0,0,0,0],"vertices":{"rawPosition":[-23,-42,0,23,-42,0,-23,42,0,23,42,0],"indexes":[0,1,2,2,1,3],"uv":[37,85,83,85,37,1,83,1],"nuv":[0.296,0.011764705882352941,0.664,0.011764705882352941,0.296,1,0.664,1],"minPos":{"x":-23,"y":-42,"z":0},"maxPos":{"x":23,"y":42,"z":0}},"packable":false,"pixelsToUnit":100,"pivot":{"x":0.5,"y":0.5},"meshType":0}],[0],0,[0],[0],[12]],[[{"name":"lajiao-lajiaozhanshidonghua_09","rect":{"x":24,"y":0,"width":74,"height":84},"offset":{"x":-1.5,"y":0.5},"originalSize":{"width":125,"height":85},"rotated":false,"capInsets":[0,0,0,0],"vertices":{"rawPosition":[-37,-42,0,37,-42,0,-37,42,0,37,42,0],"indexes":[0,1,2,2,1,3],"uv":[24,85,98,85,24,1,98,1],"nuv":[0.192,0.011764705882352941,0.784,0.011764705882352941,0.192,1,0.784,1],"minPos":{"x":-37,"y":-42,"z":0},"maxPos":{"x":37,"y":42,"z":0}},"packable":false,"pixelsToUnit":100,"pivot":{"x":0.5,"y":0.5},"meshType":0}],[0],0,[0],[0],[13]],[[{"name":"lajiao-lajiaozhanshidonghua_13","rect":{"x":10,"y":0,"width":103,"height":84},"offset":{"x":-1,"y":0.5},"originalSize":{"width":125,"height":85},"rotated":false,"capInsets":[0,0,0,0],"vertices":{"rawPosition":[-51.5,-42,0,51.5,-42,0,-51.5,42,0,51.5,42,0],"indexes":[0,1,2,2,1,3],"uv":[10,85,113,85,10,1,113,1],"nuv":[0.08,0.011764705882352941,0.904,0.011764705882352941,0.08,1,0.904,1],"minPos":{"x":-51.5,"y":-42,"z":0},"maxPos":{"x":51.5,"y":42,"z":0}},"packable":false,"pixelsToUnit":100,"pivot":{"x":0.5,"y":0.5},"meshType":0}],[0],0,[0],[0],[14]],[[{"name":"lajiao-lajiaozhanshidonghua_00","rect":{"x":53,"y":3,"width":10,"height":80},"offset":{"x":-4.5,"y":-0.5},"originalSize":{"width":125,"height":85},"rotated":false,"capInsets":[0,0,0,0],"vertices":{"rawPosition":[-5,-40,0,5,-40,0,-5,40,0,5,40,0],"indexes":[0,1,2,2,1,3],"uv":[53,82,63,82,53,2,63,2],"nuv":[0.424,0.023529411764705882,0.504,0.023529411764705882,0.424,0.9647058823529412,0.504,0.9647058823529412],"minPos":{"x":-5,"y":-40,"z":0},"maxPos":{"x":5,"y":40,"z":0}},"packable":false,"pixelsToUnit":100,"pivot":{"x":0.5,"y":0.5},"meshType":0}],[0],0,[0],[0],[15]],[[{"name":"lajiao-lajiaozhanshidonghua_03","rect":{"x":43,"y":0,"width":32,"height":83},"offset":{"x":-3.5,"y":1},"originalSize":{"width":125,"height":85},"rotated":false,"capInsets":[0,0,0,0],"vertices":{"rawPosition":[-16,-41.5,0,16,-41.5,0,-16,41.5,0,16,41.5,0],"indexes":[0,1,2,2,1,3],"uv":[43,85,75,85,43,2,75,2],"nuv":[0.344,0.023529411764705882,0.6,0.023529411764705882,0.344,1,0.6,1],"minPos":{"x":-16,"y":-41.5,"z":0},"maxPos":{"x":16,"y":41.5,"z":0}},"packable":false,"pixelsToUnit":100,"pivot":{"x":0.5,"y":0.5},"meshType":0}],[0],0,[0],[0],[16]],[[{"name":"lajiao-lajiaozhanshidonghua_20","rect":{"x":19,"y":0,"width":84,"height":84},"offset":{"x":-1.5,"y":0.5},"originalSize":{"width":125,"height":85},"rotated":false,"capInsets":[0,0,0,0],"vertices":{"rawPosition":[-42,-42,0,42,-42,0,-42,42,0,42,42,0],"indexes":[0,1,2,2,1,3],"uv":[19,85,103,85,19,1,103,1],"nuv":[0.152,0.011764705882352941,0.824,0.011764705882352941,0.152,1,0.824,1],"minPos":{"x":-42,"y":-42,"z":0},"maxPos":{"x":42,"y":42,"z":0}},"packable":false,"pixelsToUnit":100,"pivot":{"x":0.5,"y":0.5},"meshType":0}],[0],0,[0],[0],[17]],[[{"name":"lajiao-lajiaozhanshidonghua_06","rect":{"x":34,"y":0,"width":52,"height":84},"offset":{"x":-2.5,"y":0.5},"originalSize":{"width":125,"height":85},"rotated":false,"capInsets":[0,0,0,0],"vertices":{"rawPosition":[-26,-42,0,26,-42,0,-26,42,0,26,42,0],"indexes":[0,1,2,2,1,3],"uv":[34,85,86,85,34,1,86,1],"nuv":[0.272,0.011764705882352941,0.688,0.011764705882352941,0.272,1,0.688,1],"minPos":{"x":-26,"y":-42,"z":0},"maxPos":{"x":26,"y":42,"z":0}},"packable":false,"pixelsToUnit":100,"pivot":{"x":0.5,"y":0.5},"meshType":0}],[0],0,[0],[0],[18]],[[{"name":"lajiao-lajiaozhanshidonghua_25","rect":{"x":26,"y":0,"width":69,"height":84},"offset":{"x":-2,"y":0.5},"originalSize":{"width":125,"height":85},"rotated":false,"capInsets":[0,0,0,0],"vertices":{"rawPosition":[-34.5,-42,0,34.5,-42,0,-34.5,42,0,34.5,42,0],"indexes":[0,1,2,2,1,3],"uv":[26,85,95,85,26,1,95,1],"nuv":[0.208,0.011764705882352941,0.76,0.011764705882352941,0.208,1,0.76,1],"minPos":{"x":-34.5,"y":-42,"z":0},"maxPos":{"x":34.5,"y":42,"z":0}},"packable":false,"pixelsToUnit":100,"pivot":{"x":0.5,"y":0.5},"meshType":0}],[0],0,[0],[0],[19]],[[{"name":"lajiao-lajiaozhanshidonghua_04","rect":{"x":40,"y":1,"width":39,"height":83},"offset":{"x":-3,"y":0},"originalSize":{"width":125,"height":85},"rotated":false,"capInsets":[0,0,0,0],"vertices":{"rawPosition":[-19.5,-41.5,0,19.5,-41.5,0,-19.5,41.5,0,19.5,41.5,0],"indexes":[0,1,2,2,1,3],"uv":[40,84,79,84,40,1,79,1],"nuv":[0.32,0.011764705882352941,0.632,0.011764705882352941,0.32,0.9882352941176471,0.632,0.9882352941176471],"minPos":{"x":-19.5,"y":-41.5,"z":0},"maxPos":{"x":19.5,"y":41.5,"z":0}},"packable":false,"pixelsToUnit":100,"pivot":{"x":0.5,"y":0.5},"meshType":0}],[0],0,[0],[0],[20]],[[{"name":"lajiao-lajiaozhanshidonghua_21","rect":{"x":28,"y":0,"width":65,"height":84},"offset":{"x":-2,"y":0.5},"originalSize":{"width":125,"height":85},"rotated":false,"capInsets":[0,0,0,0],"vertices":{"rawPosition":[-32.5,-42,0,32.5,-42,0,-32.5,42,0,32.5,42,0],"indexes":[0,1,2,2,1,3],"uv":[28,85,93,85,28,1,93,1],"nuv":[0.224,0.011764705882352941,0.744,0.011764705882352941,0.224,1,0.744,1],"minPos":{"x":-32.5,"y":-42,"z":0},"maxPos":{"x":32.5,"y":42,"z":0}},"packable":false,"pixelsToUnit":100,"pivot":{"x":0.5,"y":0.5},"meshType":0}],[0],0,[0],[0],[21]],[[{"name":"lajiao-lajiaozhanshidonghua_01","rect":{"x":50,"y":1,"width":17,"height":82},"offset":{"x":-4,"y":0.5},"originalSize":{"width":125,"height":85},"rotated":false,"capInsets":[0,0,0,0],"vertices":{"rawPosition":[-8.5,-41,0,8.5,-41,0,-8.5,41,0,8.5,41,0],"indexes":[0,1,2,2,1,3],"uv":[50,84,67,84,50,2,67,2],"nuv":[0.4,0.023529411764705882,0.536,0.023529411764705882,0.4,0.9882352941176471,0.536,0.9882352941176471],"minPos":{"x":-8.5,"y":-41,"z":0},"maxPos":{"x":8.5,"y":41,"z":0}},"packable":false,"pixelsToUnit":100,"pivot":{"x":0.5,"y":0.5},"meshType":0}],[0],0,[0],[0],[22]],[[{"name":"lajiao-lajiaozhanshidonghua_02","rect":{"x":47,"y":1,"width":24,"height":82},"offset":{"x":-3.5,"y":0.5},"originalSize":{"width":125,"height":85},"rotated":false,"capInsets":[0,0,0,0],"vertices":{"rawPosition":[-12,-41,0,12,-41,0,-12,41,0,12,41,0],"indexes":[0,1,2,2,1,3],"uv":[47,84,71,84,47,2,71,2],"nuv":[0.376,0.023529411764705882,0.568,0.023529411764705882,0.376,0.9882352941176471,0.568,0.9882352941176471],"minPos":{"x":-12,"y":-41,"z":0},"maxPos":{"x":12,"y":41,"z":0}},"packable":false,"pixelsToUnit":100,"pivot":{"x":0.5,"y":0.5},"meshType":0}],[0],0,[0],[0],[23]],[[{"name":"lajiao-lajiaozhanshidonghua_14","rect":{"x":7,"y":0,"width":110,"height":84},"offset":{"x":-0.5,"y":0.5},"originalSize":{"width":125,"height":85},"rotated":false,"capInsets":[0,0,0,0],"vertices":{"rawPosition":[-55,-42,0,55,-42,0,-55,42,0,55,42,0],"indexes":[0,1,2,2,1,3],"uv":[7,85,117,85,7,1,117,1],"nuv":[0.056,0.011764705882352941,0.936,0.011764705882352941,0.056,1,0.936,1],"minPos":{"x":-55,"y":-42,"z":0},"maxPos":{"x":55,"y":42,"z":0}},"packable":false,"pixelsToUnit":100,"pivot":{"x":0.5,"y":0.5},"meshType":0}],[0],0,[0],[0],[24]],[[{"name":"lajiao-lajiaozhanshidonghua_17","rect":{"x":1,"y":0,"width":124,"height":84},"offset":{"x":0.5,"y":0.5},"originalSize":{"width":125,"height":85},"rotated":false,"capInsets":[0,0,0,0],"vertices":{"rawPosition":[-62,-42,0,62,-42,0,-62,42,0,62,42,0],"indexes":[0,1,2,2,1,3],"uv":[1,85,125,85,1,1,125,1],"nuv":[0.008,0.011764705882352941,1,0.011764705882352941,0.008,1,1,1],"minPos":{"x":-62,"y":-42,"z":0},"maxPos":{"x":62,"y":42,"z":0}},"packable":false,"pixelsToUnit":100,"pivot":{"x":0.5,"y":0.5},"meshType":0}],[0],0,[0],[0],[25]]]]
